sfplot/__init__.py
sfplot/search_core.py
sfplot/search_from_boxplot.py
sfplot/search_from_plot.py
sfplot/search_from_scatter.py
sfplot-0.0.1.dist-info/METADATA
sfplot-0.0.1.dist-info/WHEEL
sfplot-0.0.1.dist-info/top_level.txt
sfplot-0.0.1.dist-info/RECORD
