Metadata-Version: 2.1
Name: sfplot
Version: 0.0.1
Summary: Search records of pandas dataframe from plot.
Home-page: https://gitlab.com/kegeppa
Author: kegeppa
Author-email: 
Maintainer: kegeppa
Maintainer-email: 
License: MIT
Platform: UNKNOWN
Classifier: Programming Language :: Python :: 3
Requires-Dist: numpy
Requires-Dist: pandas
Requires-Dist: matplotlib
